MANIFEST.in
README.rst
pywinpath.py
setup.py
test_pywinpath.py
pywinpath.egg-info/PKG-INFO
pywinpath.egg-info/SOURCES.txt
pywinpath.egg-info/dependency_links.txt
pywinpath.egg-info/entry_points.txt
pywinpath.egg-info/requires.txt
pywinpath.egg-info/top_level.txt