Metadata-Version: 1.1
Name: pywinpath
Version: 2016.5.3b3
Summary: A command-line utility for MS Windows to keep the Windows PATH variable tidy and short.
Home-page: https://github.com/czamb/PyWinPath
Author: czam.de
Author-email: pywinpath@ca.czam.de
License: BSD
Keywords: PATH,Windows,cmd.exe,console,system search path,registry
Platform: UNKNOWN
Classifier: Development Status :: 4 - Beta
Classifier: Environment :: Console
Classifier: Environment :: Win32 (MS Windows)
Classifier: Intended Audience :: Developers
Classifier: Natural Language :: English
Classifier: Operating System :: Microsoft :: Windows
Classifier: Operating System :: Microsoft :: Windows :: Windows 7
Classifier: License :: OSI Approved :: BSD License
Classifier: Programming Language :: Python
Classifier: Programming Language :: Python :: 3
Classifier: Programming Language :: Python :: 3.5
Classifier: Programming Language :: Python :: Implementation :: CPython
Classifier: Topic :: Utilities
